PythonspotZhongwenXilieJiaocheng/README.md
PythonspotZhongwenXilieJiaocheng/__init__.py
PythonspotZhongwenXilieJiaocheng/__main__.py
PythonspotZhongwenXilieJiaocheng/file.epub
PythonspotZhongwenXilieJiaocheng/index.html
PythonspotZhongwenXilieJiaocheng/css/__init__.py
PythonspotZhongwenXilieJiaocheng/css/annotations.css
PythonspotZhongwenXilieJiaocheng/css/main.css
PythonspotZhongwenXilieJiaocheng/css/normalize.css
PythonspotZhongwenXilieJiaocheng/css/popup.css
PythonspotZhongwenXilieJiaocheng/font/__init__.py
PythonspotZhongwenXilieJiaocheng/font/fontello.eot
PythonspotZhongwenXilieJiaocheng/font/fontello.svg
PythonspotZhongwenXilieJiaocheng/font/fontello.ttf
PythonspotZhongwenXilieJiaocheng/font/fontello.woff
PythonspotZhongwenXilieJiaocheng/img/__init__.py
PythonspotZhongwenXilieJiaocheng/img/annotator-glyph-sprite.png
PythonspotZhongwenXilieJiaocheng/img/annotator-icon-sprite.png
PythonspotZhongwenXilieJiaocheng/img/apple-touch-icon.png
PythonspotZhongwenXilieJiaocheng/img/cancelfullscreen.png
PythonspotZhongwenXilieJiaocheng/img/close.png
PythonspotZhongwenXilieJiaocheng/img/fullscreen.png
PythonspotZhongwenXilieJiaocheng/img/loader.gif
PythonspotZhongwenXilieJiaocheng/img/menu-icon.png
PythonspotZhongwenXilieJiaocheng/img/save.png
PythonspotZhongwenXilieJiaocheng/img/saved.png
PythonspotZhongwenXilieJiaocheng/img/settings-s.png
PythonspotZhongwenXilieJiaocheng/img/settings.png
PythonspotZhongwenXilieJiaocheng/img/star.png
PythonspotZhongwenXilieJiaocheng/js/__init__.py
PythonspotZhongwenXilieJiaocheng/js/epub.js
PythonspotZhongwenXilieJiaocheng/js/epub.min.js
PythonspotZhongwenXilieJiaocheng/js/epub.min.map
PythonspotZhongwenXilieJiaocheng/js/hooks.min.js
PythonspotZhongwenXilieJiaocheng/js/hooks.min.map
PythonspotZhongwenXilieJiaocheng/js/reader.js
PythonspotZhongwenXilieJiaocheng/js/reader.js.map
PythonspotZhongwenXilieJiaocheng/js/reader.min.js
PythonspotZhongwenXilieJiaocheng/js/reader.min.map
PythonspotZhongwenXilieJiaocheng/js/hooks/__init__.py
pythonspot_zhongwen_xilie_jiaocheng-2024.3.5.0.dist-info/METADATA
pythonspot_zhongwen_xilie_jiaocheng-2024.3.5.0.dist-info/WHEEL
pythonspot_zhongwen_xilie_jiaocheng-2024.3.5.0.dist-info/entry_points.txt
pythonspot_zhongwen_xilie_jiaocheng-2024.3.5.0.dist-info/top_level.txt
pythonspot_zhongwen_xilie_jiaocheng-2024.3.5.0.dist-info/RECORD
